Terminatetensorflow/CNN_Saver.py
Terminatetensorflow/LeNet.py
Terminatetensorflow/LiveAnimation.py
Terminatetensorflow/Preprocessing.py
Terminatetensorflow/__init__.py
Terminatetensorflow/actvfn.py
Terminatetensorflow/conv.py
Terminatetensorflow/dense.py
Terminatetensorflow/loss.py
Terminatetensorflow/metrics.py
Terminatetensorflow/model.py
Terminatetensorflow/pool.py
Terminatetensorflow/saver.py
Terminatetensorflow/viz.py
Terminatetensorflow-0.0.8.dist-info/METADATA
Terminatetensorflow-0.0.8.dist-info/WHEEL
Terminatetensorflow-0.0.8.dist-info/license.txt
Terminatetensorflow-0.0.8.dist-info/top_level.txt
Terminatetensorflow-0.0.8.dist-info/RECORD
